funity/__init__.py
funity/__main__.py
funity/funity_editor.py
funity/unity_editor.py
funity/unity_project.py
funity/unity_version.py
funity/util.py
funity/data/Editor/SetSerializationMode.cs
funity/data/Editor/Utils.cs
funity-0.0.11.dist-info/LICENSE
funity-0.0.11.dist-info/METADATA
funity-0.0.11.dist-info/WHEEL
funity-0.0.11.dist-info/entry_points.txt
funity-0.0.11.dist-info/top_level.txt
funity-0.0.11.dist-info/RECORD
