Metadata-Version: 2.1
Name: funity
Version: 0.0.11
Summary: A Unity3d installation finder and a command line helper.
Home-page: https://github.com/fopoon/funity
Author: Elmer Nocon, fopoon
Author-email: elmernocon@gmail.com
License: MIT
Download-URL: https://pypi.org/project/funity/
Platform: Any
Classifier: Development Status :: 1 - Planning
Classifier: License :: OSI Approved :: MIT License
Classifier: Operating System :: MacOS :: MacOS X
Classifier: Operating System :: Microsoft :: Windows :: Windows 10
Classifier: Operating System :: Unix
Classifier: Programming Language :: Python :: 3
Classifier: Programming Language :: Python :: 3.7
Classifier: Programming Language :: Python :: 3.8
Classifier: Programming Language :: Python :: 3.9
Classifier: Programming Language :: Python :: 3 :: Only
Requires-Dist: PyYAML
